[
  {
    "name": "nlbi_2309956_2147483392",
    "value": "ytZVDTItxQWGKlcUDdoUbgAAAABCVlEFW47vY2n7AcaP1aIO",
    "domain": ".tunisair.com",
    "path": "/",
    "expires": -1,
    "size": 71,
    "httpOnly": false,
    "secure": true,
    "session": true,
    "sameSite": "None",
    "sameParty": false,
    "sourceScheme": "Secure",
    "sourcePort": 443
  },
  {
    "name": "_dd1A",
    "value": "iPp1augYdOssOVN1D_LHAYCOTTmWDKKCS7RzKAQw!16804735002571680473503.154",
    "domain": ".book.tunisair.com",
    "path": "/",
    "expires": 1712190420.943578,
    "size": 73,
    "httpOnly": true,
    "secure": true,
    "session": false,
    "sameParty": false,
    "sourceScheme": "Secure",
    "sourcePort": 443
  },
  {
    "name": "incap-resubmit-token",
    "value": "mybFudawzmA=:Zuear10c1okdi1ywZFgcrr1LH6R/0vOjItJFKca31RE=",
    "domain": "book.tunisair.com",
    "path": "/",
    "expires": 1680568075.881565,
    "size": 77,
    "httpOnly": true,
    "secure": true,
    "session": false,
    "sameSite": "None",
    "sameParty": false,
    "sourceScheme": "Secure",
    "sourcePort": 443
  },
  {
    "name": "__utmz",
    "value": "266893195.1680566567.1.1.utmcsr=(direct)|utmccn=(direct)|utmcmd=(none)",
    "domain": ".tunisair.com",
    "path": "/",
    "expires": 1696334567,
    "size": 76,
    "httpOnly": false,
    "secure": false,
    "session": false,
    "sameParty": false,
    "sourceScheme": "Secure",
    "sourcePort": 443
  },
  {
    "name": "__utma",
    "value": "266893195.549788904.1680473505.1680566567.1680566567.1",
    "domain": ".tunisair.com",
    "path": "/",
    "expires": 1715126567.049834,
    "size": 60,
    "httpOnly": false,
    "secure": false,
    "session": false,
    "sameParty": false,
    "sourceScheme": "Secure",
    "sourcePort": 443
  },
  {
    "name": "_fbp",
    "value": "fb.1.1680566569635.647941230",
    "domain": ".tunisair.com",
    "path": "/",
    "expires": 1688342611,
    "size": 32,
    "httpOnly": false,
    "secure": false,
    "session": false,
    "sameSite": "Lax",
    "sameParty": false,
    "sourceScheme": "Secure",
    "sourcePort": 443
  },
  {
    "name": "__utmb",
    "value": "266893195.1.10.1680566567",
    "domain": ".tunisair.com",
    "path": "/",
    "expires": 1680568367,
    "size": 31,
    "httpOnly": false,
    "secure": false,
    "session": false,
    "sameParty": false,
    "sourceScheme": "Secure",
    "sourcePort": 443
  },
  {
    "name": "BIGipServer~ETV~ns_fran-prd_praxis_80_pool",
    "value": "!X8C4E6hvV9gJjYutmW5vQEgjq3si3UZ7pBPUOh2YsuuQm4RT7FaXrRQFQObcxUjXIl8ntLIxym58m0I/YGN/oS/6MH2YEAXIP0bMHDY=",
    "domain": "book.tunisair.com",
    "path": "/",
    "expires": -1,
    "size": 147,
    "httpOnly": true,
    "secure": true,
    "session": true,
    "sameSite": "None",
    "sameParty": false,
    "sourceScheme": "Secure",
    "sourcePort": 443
  },
  {
    "name": "70657fe77a019424c4787a5f4e9c9d66",
    "value": "278dce54d676d1be53b2e22203f8a2c4",
    "domain": "book.tunisair.com",
    "path": "/",
    "expires": -1,
    "size": 64,
    "httpOnly": true,
    "secure": false,
    "session": true,
    "sameParty": false,
    "sourceScheme": "Secure",
    "sourcePort": 443
  },
  {
    "name": "DWM_XSITECODE",
    "value": "BASXBNEW",
    "domain": "book.tunisair.com",
    "path": "/",
    "expires": -1,
    "size": 21,
    "httpOnly": true,
    "secure": true,
    "session": true,
    "sameParty": false,
    "sourceScheme": "Secure",
    "sourcePort": 443
  },
  {
    "name": "incap_sh_2309956",
    "value": "m24rZAAAAACrQ7pKDAAIm92toQYQit2toQb/aNf9w9rnKv/t8WGMGeVp",
    "domain": "book.tunisair.com",
    "path": "/",
    "expires": 1680571563.957787,
    "size": 72,
    "httpOnly": true,
    "secure": true,
    "session": false,
    "sameSite": "None",
    "sameParty": false,
    "sourceScheme": "Secure",
    "sourcePort": 443
  },
  {
    "name": "1a504a7bd538aeabd631da6a5298dcb2",
    "value": "bf9b8aaea20464c2508e9044e83cf18d",
    "domain": "book.tunisair.com",
    "path": "/",
    "expires": -1,
    "size": 64,
    "httpOnly": true,
    "secure": false,
    "session": true,
    "sameParty": false,
    "sourceScheme": "Secure",
    "sourcePort": 443
  },
  {
    "name": "um_jst",
    "value": "983F537C5063F143E79024DF89365C123944D4CFE05E87415A0D7DF3273E3AF0",
    "domain": "book.tunisair.com",
    "path": "/",
    "expires": -1,
    "size": 70,
    "httpOnly": true,
    "secure": true,
    "session": true,
    "sameSite": "None",
    "sameParty": false,
    "sourceScheme": "Secure",
    "sourcePort": 443
  },
  {
    "name": "incap_ses_8077_2309956",
    "value": "+u6eVtjeBxdq10+EXEUXcCJjK2QAAAAA8W8pcms1huEOFEekgHDJ8g==",
    "domain": ".tunisair.com",
    "path": "/",
    "expires": -1,
    "size": 78,
    "httpOnly": false,
    "secure": true,
    "session": true,
    "sameSite": "None",
    "sameParty": false,
    "sourceScheme": "Secure",
    "sourcePort": 443
  },
  {
    "name": "_gat_gaDigitalData",
    "value": "1",
    "domain": ".tunisair.com",
    "path": "/",
    "expires": 1680568047,
    "size": 19,
    "httpOnly": false,
    "secure": false,
    "session": false,
    "sameParty": false,
    "sourceScheme": "Secure",
    "sourcePort": 443
  },
  {
    "name": "incap_ses_466_2309956",
    "value": "InrTKMVSlWHYcgGWbpF3Bl9aK2QAAAAA09EBeh6pT1bZZRsx3x34Ww==",
    "domain": ".tunisair.com",
    "path": "/",
    "expires": -1,
    "size": 77,
    "httpOnly": false,
    "secure": true,
    "session": true,
    "sameSite": "None",
    "sameParty": false,
    "sourceScheme": "Secure",
    "sourcePort": 443
  },
  {
    "name": "visid_incap_2309956",
    "value": "ehtmBXvPTOqvyIgR5b8BP5H9KWQAAAAAT0IPAAAAAACA+mOrAWaeCwP3s6nZe98M8K+U8y+F2Pjb",
    "domain": ".tunisair.com",
    "path": "/",
    "expires": 1712096316.807789,
    "size": 95,
    "httpOnly": true,
    "secure": true,
    "session": false,
    "sameSite": "None",
    "sameParty": false,
    "sourceScheme": "Secure",
    "sourcePort": 443
  },
  {
    "name": "_ga",
    "value": "GA1.2.549788904.1680473505",
    "domain": ".tunisair.com",
    "path": "/",
    "expires": 1715128014.248406,
    "size": 29,
    "httpOnly": false,
    "secure": false,
    "session": false,
    "sameParty": false,
    "sourceScheme": "Secure",
    "sourcePort": 443
  },
  {
    "name": "incap_ses_189_2309956",
    "value": "j3rYEJxThhhbbG7c43afAjH/KWQAAAAAp+t80ML1XFCPQ228uqnpww==",
    "domain": ".tunisair.com",
    "path": "/",
    "expires": -1,
    "size": 77,
    "httpOnly": false,
    "secure": true,
    "session": true,
    "sameSite": "None",
    "sameParty": false,
    "sourceScheme": "Secure",
    "sourcePort": 443
  },
  {
    "name": "SITE",
    "value": "BASXBNEW",
    "domain": "book.tunisair.com",
    "path": "/",
    "expires": -1,
    "size": 12,
    "httpOnly": false,
    "secure": false,
    "session": true,
    "sameParty": false,
    "sourceScheme": "Secure",
    "sourcePort": 443
  },
  {
    "name": "nlbi_2309956",
    "value": "BzCcYOW94UQoZsvvDdoUbgAAAADmlK6yRMkIxkfENwQ7VCdx",
    "domain": ".tunisair.com",
    "path": "/",
    "expires": -1,
    "size": 60,
    "httpOnly": false,
    "secure": true,
    "session": true,
    "sameSite": "None",
    "sameParty": false,
    "sourceScheme": "Secure",
    "sourcePort": 443
  },
  {
    "name": "incap_ses_1517_2309956",
    "value": "OBKtOqnut1oGnoHa43cNFWJeK2QAAAAAn/bHudtOGc1joOXGMAO0Kg==",
    "domain": ".tunisair.com",
    "path": "/",
    "expires": -1,
    "size": 78,
    "httpOnly": false,
    "secure": true,
    "session": true,
    "sameSite": "None",
    "sameParty": false,
    "sourceScheme": "Secure",
    "sourcePort": 443
  },
  {
    "name": "_gid",
    "value": "GA1.2.1017211754.1680562982",
    "domain": ".tunisair.com",
    "path": "/",
    "expires": 1680654414,
    "size": 31,
    "httpOnly": false,
    "secure": false,
    "session": false,
    "sameParty": false,
    "sourceScheme": "Secure",
    "sourcePort": 443
  },
  {
    "name": "incap_ses_390_2309956",
    "value": "u+cVdzdrMxHxLm/1yY9pBS8CKmQAAAAAdQiPH4NELYfXjchv4qKn3w==",
    "domain": ".tunisair.com",
    "path": "/",
    "expires": -1,
    "size": 77,
    "httpOnly": false,
    "secure": true,
    "session": true,
    "sameSite": "None",
    "sameParty": false,
    "sourceScheme": "Secure",
    "sourcePort": 443
  },
  {
    "name": "incap_ses_1516_2309956",
    "value": "14x2XPo3w1xpYKtDc+oJFZH9KWQAAAAAv3UJR8k6xcSUkM/KFcLX1w==",
    "domain": ".tunisair.com",
    "path": "/",
    "expires": -1,
    "size": 78,
    "httpOnly": false,
    "secure": true,
    "session": true,
    "sameSite": "None",
    "sameParty": false,
    "sourceScheme": "Secure",
    "sourcePort": 443
  },
  {
    "name": "reese84",
    "value": "3:7H+Yfgfb3rQbNocoJhVurg==:E5yUA5RCf7s+gk1uv4HUVkysDPvsk8cgSu4PR/tPYmor97s+KZhjV/6bnaz4tK34pQV9pdMCA18710rHAcu4emAXRGymGUIWl3i8Vy3RDgb5Df/fEQYrapG9ds/5RxPOPTJEVh3POjH545iEu1QV3dvLIzYbAy4miKT2I+DBUrMlAN9RXH0xNZsnxoAfs+2Fg46/QQRJ6OyE9NCrNGqvDBtIAMHKkoeD0fG2I1J62C04/BJRC9ygw4Ys4JCefZLy/9RauEe7ORYJmtS0H2cFyVqQD4HEQ9L9H5eq5Jv4e2VgpUNDuesvVYntBpNvtALeNhTqEi11IOqX9FIH8ikqNVU5wVdZguKjWPVfDxWU4H5BX/0zVX9qLRbuMC8mS9PUJ5EVmUg79K8EU4LRjmOlSNA3LBN2HQ/7jCD7otraVQ+766lrqvLQ61gXa4rX/PRcArNsB5wWIVOyQnzu6etjGLEgiKA1uqf3gcFo1kKzf6ocagMa8sDFJBt3BqgHT8Z7T7Psmwta39zLw5GO24sKDrt5+TNLbFf7bH58KPSVUW9Ee3mQEapuOrGiCJv6TA1oLg8ZMTU5GXcXX2m8Wow6cfWTLFyOqO/SzPXQ2s195UvSOPxGbo+GGff6DGCfOGVij/dj9BPGTinVNY7RFV5mfwECfW+7SjlvDtvXFc1tXRldHiyZrKSrKoK0biEz48b/MNHTeqG7FcNInLpwhtmZU0BZz81IrCvMs5r50QiOv0g=:2p38Gcc5ueMwtwHoXV6d7anFYeJ9lDMApV5Evf4eRyY=",
    "domain": ".tunisair.com",
    "path": "/",
    "expires": 1683160020.344779,
    "size": 827,
    "httpOnly": false,
    "secure": false,
    "session": false,
    "sameSite": "Lax",
    "sameParty": false,
    "sourceScheme": "Secure",
    "sourcePort": 443
  }
]